jupancon/__init__.py
jupancon/config.py
jupancon/core.py
jupancon/defaults.py
jupancon/magic.py
jupancon/engine/__init__.py
jupancon/engine/databricks.py
jupancon-0.3.3.dist-info/LICENSE.md
jupancon-0.3.3.dist-info/WHEEL
jupancon-0.3.3.dist-info/METADATA
jupancon-0.3.3.dist-info/RECORD
