Metadata-Version: 2.1
Name: jupancon
Version: 0.3.3
Summary: Jupancon, connector to several DBs that returns pandas. Magic included.
Author-email: Juan González-Vallinas <juan@multilayer.io>
Classifier: License :: OSI Approved :: MIT License
Requires-Dist: pandas<2.0.0
Requires-Dist: sshtunnel>=0.4.0
Requires-Dist: pyparsing>=3.0.9
Requires-Dist: sqlalchemy-redshift>=0.8.14
Requires-Dist: redshift-connector>=2.0.911
Requires-Dist: databricks-sql-connector>=2.6.1
Requires-Dist: sqlalchemy-bigquery>=1.6.1
Requires-Dist: google-cloud-bigquery-storage>=2.20.0
Requires-Dist: pytest>=6.2.5 ; extra == "test"
Requires-Dist: jupyter>=1.0.0 ; extra == "test"
Requires-Dist: jupyterlab>=3.1.14 ; extra == "test"
Requires-Dist: black>=21.9b0 ; extra == "test"
Requires-Dist: flake8>=3.9.2 ; extra == "test"
Requires-Dist: isort>=5.9.3 ; extra == "test"
Project-URL: Home, https://github.com/multilayer-io/jupancon
Provides-Extra: test
